youtube_transcriber/__init__.py
youtube_transcriber/main.py
youtube_transcriber/setup.py
youtube_transcriber/gui/__init__.py
youtube_transcriber/gui/transcriber.py
youtube_transcriber1-1.1.0.dist-info/METADATA
youtube_transcriber1-1.1.0.dist-info/WHEEL
youtube_transcriber1-1.1.0.dist-info/entry_points.txt
youtube_transcriber1-1.1.0.dist-info/top_level.txt
youtube_transcriber1-1.1.0.dist-info/RECORD
