Metadata-Version: 2.1
Name: youtube-transcriber1
Version: 1.1.0
Requires-Dist: pytube
Requires-Dist: whisper
